pg_schema_version/__init__.py
pg_schema_version/psql.py
pg_schema_version/script.py
pg_schema_version/utils.py
pg_schema_version-1.0.dist-info/licenses/LICENSE
pg_schema_version-1.0.dist-info/METADATA
pg_schema_version-1.0.dist-info/WHEEL
pg_schema_version-1.0.dist-info/entry_points.txt
pg_schema_version-1.0.dist-info/top_level.txt
pg_schema_version-1.0.dist-info/RECORD
