Metadata-Version: 2.4
Name: pg-schema-version
Version: 1.0
Summary: Simple Postgres Schema Versioning
Author: Fabien Coelho
License-Expression: CC0-1.0
Project-URL: repository, https://github.com/zx80/pg-schema-version
Project-URL: documentation, https://zx80.github.io/pg-schema-version/
Project-URL: issues, https://github.com/zx80/pg-schema-version/issues
Project-URL: package, https://pypi.org/project/pg-schema-version
Classifier: Topic :: Software Development
Classifier: Topic :: Database
Classifier: Programming Language :: Python
Classifier: Programming Language :: SQL
Classifier: Development Status :: 5 - Production/Stable
Requires-Python: >=3.10
License-File: LICENSE
Provides-Extra: dev
Requires-Dist: pyright; extra == "dev"
Requires-Dist: ruff; extra == "dev"
Requires-Dist: coverage; extra == "dev"
Requires-Dist: pymarkdownlnt; extra == "dev"
Provides-Extra: pub
Requires-Dist: build; extra == "pub"
Requires-Dist: twine; extra == "pub"
Requires-Dist: wheel; extra == "pub"
Dynamic: license-file
